spypointapi/__init__.py
spypointapi/spypoint_api.py
spypointapi/spypoint_api_errors.py
spypointapi/cameras/__init__.py
spypointapi/cameras/camera.py
spypointapi/cameras/camera_api_response.py
spypointapi/shared_cameras/shared_cameras_api_response.py
spypoint_api-0.3.0.dist-info/METADATA
spypoint_api-0.3.0.dist-info/WHEEL
spypoint_api-0.3.0.dist-info/licenses/LICENSE
spypoint_api-0.3.0.dist-info/RECORD
