Metadata-Version: 2.4
Name: spypoint-api
Version: 0.3.0
Summary: Library to communicate with Spypoint REST api
Project-URL: Homepage, https://github.com/happydev-ca/spypoint-api
Project-URL: Issues, https://github.com/happydev-ca/spypoint-api/issues
Author-email: Francois Perron <fperron@gmail.com>
License-File: LICENSE
Classifier: Development Status :: 5 - Production/Stable
Classifier: License :: OSI Approved :: MIT License
Classifier: Operating System :: OS Independent
Classifier: Programming Language :: Python :: 3
Classifier: Topic :: Home Automation
Requires-Python: >=3.13
Requires-Dist: aiohttp
